pipelinescript/__init__.py
pipelinescript/__main__.py
pipelinescript/compiler.py
pipelinescript/debugger.py
pipelinescript/executor.py
pipelinescript/parser.py
pipelinescript/pipeline.py
pipelinescript/visualizer.py
pipelinescript-0.1.3.dist-info/licenses/LICENSE
pipelinescript-0.1.3.dist-info/METADATA
pipelinescript-0.1.3.dist-info/WHEEL
pipelinescript-0.1.3.dist-info/entry_points.txt
pipelinescript-0.1.3.dist-info/top_level.txt
pipelinescript-0.1.3.dist-info/RECORD
