Metadata-Version: 2.4
Name: pipelinescript
Version: 0.1.3
Summary: Human-readable ML pipeline language with DSL, debugging, and visualization
Home-page: https://github.com/idrissbado/PipelineScript
Author: Idriss Bado
Author-email: Idriss Bado <idrissbadoolivier@gmail.com>
Project-URL: Homepage, https://github.com/idrissbado/PipelineScript
Project-URL: Documentation, https://github.com/idrissbado/PipelineScript#readme
Project-URL: Repository, https://github.com/idrissbado/PipelineScript
Project-URL: Bug Tracker, https://github.com/idrissbado/PipelineScript/issues
Keywords: machine-learning,dsl,pipeline,ml-pipeline,debugging,visualization,sklearn,xgboost,domain-specific-language,data-science,automl
Classifier: Development Status :: 4 - Beta
Classifier: Intended Audience :: Developers
Classifier: Intended Audience :: Science/Research
Classifier: Topic :: Scientific/Engineering :: Artificial Intelligence
Classifier: Topic :: Software Development :: Interpreters
Classifier: License :: OSI Approved :: MIT License
Classifier: Programming Language :: Python :: 3
Classifier: Programming Language :: Python :: 3.8
Classifier: Programming Language :: Python :: 3.9
Classifier: Programming Language :: Python :: 3.10
Classifier: Programming Language :: Python :: 3.11
Classifier: Programming Language :: Python :: 3.12
Requires-Python: >=3.8
License-File: LICENSE
Requires-Dist: pandas>=1.3.0
Requires-Dist: numpy>=1.21.0
Requires-Dist: scikit-learn>=1.0.0
Provides-Extra: full
Requires-Dist: xgboost>=1.5.0; extra == "full"
Requires-Dist: matplotlib>=3.5.0; extra == "full"
Provides-Extra: xgboost
Requires-Dist: xgboost>=1.5.0; extra == "xgboost"
Provides-Extra: viz
Requires-Dist: matplotlib>=3.5.0; extra == "viz"
Provides-Extra: dev
Requires-Dist: pytest>=7.0.0; extra == "dev"
Requires-Dist: pytest-cov>=3.0.0; extra == "dev"
Requires-Dist: black>=22.0.0; extra == "dev"
Requires-Dist: flake8>=4.0.0; extra == "dev"
Dynamic: author
Dynamic: home-page
Dynamic: license-file
Dynamic: requires-python
